print_tensor/__init__.py
print_tensor/print_tensor.py
printensor-0.0.7.dist-info/METADATA
printensor-0.0.7.dist-info/WHEEL
printensor-0.0.7.dist-info/top_level.txt
printensor-0.0.7.dist-info/RECORD
