Metadata-Version: 2.1
Name: printensor
Version: 0.0.7
Summary: Print shape of pytorch tensor inside list, tuple, dict, generator
Home-page: https://github.com/wwdok/print_tensor
Author: Weida Wang
Author-email: wade.wang96@outlook.com
License: MIT License
Keywords: deep learning
Platform: all
Classifier: Development Status :: 3 - Alpha
Classifier: License :: OSI Approved :: MIT License
Classifier: Operating System :: OS Independent
Classifier: Programming Language :: Python :: 3.5
Classifier: Programming Language :: Python :: 3.6
Classifier: Programming Language :: Python :: 3.7
Classifier: Programming Language :: Python :: 3.8
